{
  "categories": [
    {
      "id": "panel-kapi",
      "name": "Panel Kapı",
      "icon": "door-open",
      "description": "Amerikan panel kapı modelleri, iç oda kapıları.",
      "subcategories": [
        "Amerikan Panel Kapı",
        "Camlı Panel Kapı"
      ]
    },
    {
      "id": "lake-kapi",
      "name": "Lake Kapı",
      "icon": "door-closed",
      "description": "Lake boyalı modern iç mekan kapıları.",
      "subcategories": [
        "Düz Lake Kapı",
        "Camlı Lake Kapı"
      ]
    },
    {
      "id": "melamin-kapi",
      "name": "Melamin Kapı",
      "icon": "door-closed",
      "description": "Dayanıklı ve şık melamin oda kapıları.",
      "subcategories": [
        "Melamin Panel",
        "Camlı Melamin"
      ]
    },
    {
      "id": "celik-kapi",
      "name": "Çelik Kapı",
      "icon": "shield",
      "description": "Güvenli ve şık çelik kapı modelleri.",
      "subcategories": [
        "Klasik Çelik Kapı",
        "Lüks Çelik Kapı",
        "Dış Mekan"
      ]
    },
    {
      "id": "mutfak-dolabi",
      "name": "Mutfak Dolabı",
      "icon": "chef-hat",
      "description": "Modern mutfak dolabı modelleri.",
      "subcategories": [
        "Hazır Mutfak",
        "Mutfak Tezgahı"
      ]
    },
    {
      "id": "banyo-dolabi",
      "name": "Banyo Dolabı",
      "icon": "bath",
      "description": "Banyo dolabı seti ve aynalı modeller.",
      "subcategories": [
        "Banyo Seti",
        "Aynalı Dolap"
      ]
    },
    {
      "id": "dusakabin",
      "name": "Duşakabin",
      "icon": "shower-head",
      "description": "Temperli camlı modern duşakabin çözümleri.",
      "subcategories": [
        "Kare Duşakabin",
        "Oval Duşakabin"
      ]
    },
    {
      "id": "pimapen",
      "name": "Pimapen",
      "icon": "window",
      "description": "PVC kapı ve pencere sistemleri.",
      "subcategories": [
        "PVC Pencere",
        "PVC Kapı"
      ]
    },
    {
      "id": "klozet-takimi",
      "name": "Klozet Takımı",
      "icon": "toilet",
      "description": "Modern klozet ve rezervuar takımları.",
      "subcategories": [
        "Gömme Rezervuar",
        "Klozet Seti"
      ]
    },
    {
      "id": "musluk-batarya",
      "name": "Musluk & Batarya",
      "icon": "pipette",
      "image": "https://www.isaogluyapi.com/idea/pc/51/myassets/products/742/1-org-zoom.jpg?revision=1727450974",
      "description": "Şık musluk ve batarya modelleri.",
      "subcategories": [
        "Banyo Bataryası",
        "Mutfak Bataryası"
      ]
    },
    {
      "id": "kilit-kol",
      "name": "Kilit & Kol",
      "icon": "key",
      "image": "https://image.made-in-china.com/202f0j00cCslnotIAGYm/Modern-High-Grade-Gray-Zinc-Alloy-Handle-Silent-Mortise-Inner-Door-Lever-Lock-Set.webp",
      "description": "Kapı kolları ve emniyetli kilit sistemleri.",
      "subcategories": [
        "Kapı Kolu",
        "Emniyet Kilidi"
      ]
    },
    {
      "id": "konteyner",
      "name": "Konteyner",
      "icon": "container",
      "description": "Prefabrik konteyner ev ve yapı çözümleri.",
      "subcategories": []
    },
    {
      "id": "komurluk-kapisi",
      "name": "Kömürlük Kapısı",
      "icon": "door-open",
      "description": "Dekoratif ferforje kömürlük ve bodrum kapıları.",
      "subcategories": []
    },
    {
      "id": "yangin-kapisi",
      "name": "Yangın Kapısı",
      "icon": "flame",
      "description": "Sertifikalı yangına dayanıklı çelik yangın kapıları.",
      "subcategories": []
    }
  ],
  "products": [
    {
      "id": 1,
      "name": "Panel Kapı - Anatolia",
      "category": "panel-kapi",
      "image": "https://amerikan-panel-kapi.com.tr/image/catalog/PANEL%20KAPI/Ankara%20Amerikan%20Panel%20Kap%C4%B1%20-%20Anatolia.png",
      "description": "Birinci sınıf Amerikan panel kapı, uzun ömürlü kullanım.",
      "isNew": true,
      "isFeatured": true
    },
    {
      "id": 2,
      "name": "Panel Kapı - Anatolia Camlı",
      "category": "panel-kapi",
      "image": "https://amerikan-panel-kapi.com.tr/image/catalog/PANEL%20KAPI/Ankara%20Amerikan%20Panel%20Kap%C4%B1%20-%20Anatolia%20Caml%C4%B1.png",
      "description": "Camlı şık tasarım Amerikan panel oda kapısı."
    },
    {
      "id": 3,
      "name": "Panel Kapı - Bolu",
      "category": "panel-kapi",
      "image": "https://amerikan-panel-kapi.com.tr/image/catalog/PANEL%20KAPI/Ankara%20Amerikan%20Panel%20Kap%C4%B1%20_Bolu.png",
      "description": "Klasik ve dayanıklı Bolu modeli ahşap görünümlü panel kapı."
    },
    {
      "id": 4,
      "name": "Panel Kapı - Bolu Camlı",
      "category": "panel-kapi",
      "image": "https://amerikan-panel-kapi.com.tr/image/catalog/PANEL%20KAPI/Ankara%20Amerikan%20Panel%20Kap%C4%B1%20_%20Bolu%20Caml%C4%B1.png",
      "description": "Cam detaylı zarif Bolu modeli oda kapısı."
    },
    {
      "id": 5,
      "name": "Panel Kapı - Efes",
      "category": "panel-kapi",
      "image": "https://amerikan-panel-kapi.com.tr/image/catalog/PANEL%20KAPI/Ankara%20Amerikan%20Panel%20Kap%C4%B1_Efes.png",
      "description": "Sağlam ve uzun yıllar kullanılabilir Efes modeli panel kapı."
    },
    {
      "id": 7,
      "name": "Panel Kapı - Hitit",
      "category": "panel-kapi",
      "image": "https://amerikan-panel-kapi.com.tr/image/catalog/PANEL%20KAPI/Ankara%20Amerikan%20Panel%20Kap%C4%B1%20_Hitit.png",
      "description": "Geleneksel çizgiler taşıyan Hitit modeli Amerikan kapı."
    },
    {
      "id": 8,
      "name": "Panel Kapı - Hitit Camlı",
      "category": "panel-kapi",
      "image": "https://amerikan-panel-kapi.com.tr/image/catalog/PANEL%20KAPI/Ankara%20Amerikan%20Panel%20Kap%C4%B1%20Hitit%20Caml%C4%B1.png",
      "description": "Camlı ve şık Hitit modeli iç oda kapısı."
    },
    {
      "id": 10,
      "name": "Panel Kapı - Milano",
      "category": "panel-kapi",
      "image": "https://amerikan-panel-kapi.com.tr/image/catalog/PANEL%20KAPI/Ankara%20Amerikan%20Panel%20Kap%C4%B1%20_%20Milano.png",
      "description": "Zarif ve estetik Milano modeli panel kapı."
    },
    {
      "id": 11,
      "name": "Lake Kapı - Çapraz Çizgi",
      "category": "lake-kapi",
      "image": "https://amerikan-panel-kapi.com.tr/image/catalog/LAKE%20KAPI/Ankara%20Lake%20Kap%C4%B1_%C3%87arpraz%20%C3%87izgili.png",
      "description": "Modern CNC kesim beyaz lake oda kapısı.",
      "isNew": true,
      "isFeatured": true
    },
    {
      "id": 12,
      "name": "Lake Kapı - Kare Çizgi",
      "category": "lake-kapi",
      "image": "https://amerikan-panel-kapi.com.tr/image/catalog/LAKE%20KAPI/Ankara%20Lake%20Kap%C4%B1%20Kare%20%C3%87izgili.png",
      "description": "Kare desenli şık lake kapı."
    },
    {
      "id": 13,
      "name": "Lake Kapı - Boy Camlı",
      "category": "lake-kapi",
      "image": "https://amerikan-panel-kapi.com.tr/image/catalog/LAKE%20KAPI/Ankara%20Lake%20Kap%C4%B1_%20Boy%20Caml%C4%B1.png",
      "description": "Lüks boy camlı lake iç kapı."
    },
    {
      "id": 14,
      "name": "Ado Melamin Kapı - 3 Göbek",
      "category": "melamin-kapi",
      "image": "https://amerikan-panel-kapi.com.tr/image/catalog/MELAM%C4%B0N%20KAPI/Ado%20Melamin%20Kap%C4%B1%203%20G%C3%B6bek.png",
      "description": "Çizilmelere karşı ekstra dayanıklı Ado melamin kapı."
    },
    {
      "id": 15,
      "name": "Ado Melamin Kapı - Tek Göbek",
      "category": "melamin-kapi",
      "image": "https://amerikan-panel-kapi.com.tr/image/catalog/MELAM%C4%B0N%20KAPI/Ado%20Melamin%20Kap%C4%B1%20Tek%20G%C3%B6bek.png",
      "description": "Sade ve minimalist tasarımlı melamin panel kapı."
    },
    {
      "id": 16,
      "name": "Çelik Kapı - Lotus",
      "category": "celik-kapi",
      "image": "https://amerikan-panel-kapi.com.tr/image/catalog/CEL%C4%B0K%20KAPI/elik%20Kap%C4%B1%20Ankara%203.png",
      "description": "Üst düzey güvenlik sağlayan Lotus modeli çelik kapı.",
      "isNew": true,
      "isFeatured": true
    },
    {
      "id": 17,
      "name": "Çelik Kapı - Royal",
      "category": "celik-kapi",
      "image": "https://amerikan-panel-kapi.com.tr/image/catalog/CEL%C4%B0K%20KAPI/elik%20Kap%C4%B1%20Ankara%206.png",
      "description": "Premium Royal seri dış cephe çelik kapı."
    },
    {
      "id": 18,
      "name": "Mutfak Dolabı 2 Metre",
      "category": "mutfak-dolabi",
      "image": "https://amerikan-panel-kapi.com.tr/image/catalog/MUTFAK%20DOLABI/Mutfak%20Dolab%C4%B1%20Ankara%201%2C5%20Metre.jpg",
      "description": "Kullanıma hazır, pratik ve şık 2 metre mutfak dolabı.",
      "isNew": true,
      "isFeatured": true
    },
    {
      "id": 19,
      "name": "Banyo Dolabı Sandy 80cm",
      "category": "banyo-dolabi",
      "image": "https://amerikan-panel-kapi.com.tr/image/catalog/BANYO%20DOLABI/Ankara%20Banyo%20Dolab%C4%B1%20Sandy%2080cm.png",
      "description": "Modern tasarıma sahip 80cm genişliğinde Sandy banyo dolabı."
    },
    {
      "id": 20,
      "name": "Duşakabin Kare Siyah",
      "category": "dusakabin",
      "image": "https://amerikan-panel-kapi.com.tr/image/catalog/DU%C5%9EAKAB%C4%B0N/Du%C5%9Fakabin%20Kare%20Ankara%205.png",
      "description": "Temperli siyah cam kare lüks duşakabin."
    },
    {
      "id": 21,
      "name": "Pimapen Pencere 100x100",
      "category": "pimapen",
      "image": "https://amerikan-panel-kapi.com.tr/image/catalog/P%C4%B0MAPEN/Ankara%20Pimapen%20%C3%87ift%20A%C3%A7%C4%B1l%C4%B1m%2C.png",
      "description": "Isı yalıtımlı PVC çift açılım pencere sistemi."
    },
    {
      "id": 24,
      "name": "Klozet Takımı - Beyaz",
      "category": "klozet-takimi",
      "image": "products/klozet-takimi/klozet-takimi-beyaz.png",
      "description": "Birinci kalite seramikten üretilmiş tam takım klozet ve rezervuar seti.",
      "oldPrice": 8500,
      "price": 6200
    },
    {
      "id": 25,
      "name": "Prefabrik Konteyner Ev - Taş Desenli Verandalı",
      "category": "konteyner",
      "image": "assets/images/products/konteyner/konteyner1.webp",
      "description": "Taş desen kaplama, verandalı ve merdiveli prefabrik konteyner ev. Su deposu dahil, kullanıma hazır.",
      "isNew": true,
      "isFeatured": true
    },
    {
      "id": 26,
      "name": "Prefabrik Konteyner Ev - Ahşap Kompozit Cepheli",
      "category": "konteyner",
      "image": "assets/images/products/konteyner/konteyner2.webp",
      "description": "Ahşap kompozit ve antrasit gri cephe kaplamalı modern prefabrik konteyner. Geniş cam kapılı, ferah iç mekan.",
      "isNew": true,
      "isFeatured": true
    },
    {
      "id": 27,
      "name": "Kömürlük Kapısı - Ferforje Altın Desenli",
      "category": "komurluk-kapisi",
      "image": "assets/images/products/komurluk-kapisi/komurluk-kapisi-1.jpg",
      "description": "Dekoratif ferforje işlemeli, altın detaylı kömürlük ve bodrum giriş kapısı. Sağlam çelik konstrüksiyon.",
      "isNew": true,
      "isFeatured": true
    },
    {
      "id": 28,
      "name": "Banyo Dolabı - Aynalı Mermer Desenli",
      "category": "banyo-dolabi",
      "image": "assets/images/products/banyo-dolabi/banyo-dolabi-aynali-mermer.jpg",
      "description": "Mermer ve ahşap detaylı aynalı banyo dolabı seti. Seramik lavabo dahil.",
      "isNew": true
    },
    {
      "id": 29,
      "name": "Banyo Dolabı - Aynalı Siyah Mermer",
      "category": "banyo-dolabi",
      "image": "assets/images/products/banyo-dolabi/banyo-dolabi-aynali-siyah.jpg",
      "description": "Siyah mermer detaylı modern aynalı banyo dolabı. Geniş ayna ve seramik lavabo.",
      "isNew": true
    },
    {
      "id": 30,
      "name": "Mutfak Dolabı - Klasik Beyaz",
      "category": "mutfak-dolabi",
      "image": "assets/images/products/mutfak-dolabi/mutfak-dolabi-klasik-beyaz.jpg",
      "description": "Klasik profilli beyaz mutfak dolabı seti. Alt ve üst dolaplar dahil, mermer tezgahlı.",
      "isNew": true
    },
    {
      "id": 31,
      "name": "Mutfak Dolabı - Modern Ahşap",
      "category": "mutfak-dolabi",
      "image": "assets/images/products/mutfak-dolabi/mutfak-dolabi-modern-ahsap.jpg",
      "description": "Ahşap alt dolap ve beyaz üst dolaplı modern mutfak dolabı seti. Davlumbaz bölmeli.",
      "isNew": true
    },
    {
      "id": 32,
      "name": "Banyo Dolabı Seti - Boy Dolaplı",
      "category": "banyo-dolabi",
      "image": "assets/images/products/banyo-dolabi/banyo-dolabi-boy-dolapli.jpg",
      "description": "Aynalı üst dolap, seramik lavabo ve boy dolabından oluşan komple banyo seti.",
      "isNew": true
    },
    {
      "id": 33,
      "name": "Banyo Dolabı - Aynalı Minimal Beyaz",
      "category": "banyo-dolabi",
      "image": "assets/images/products/banyo-dolabi/banyo-dolabi-aynali-minimal.jpg",
      "description": "Minimalist tasarımlı aynalı beyaz banyo dolabı. Dikdörtgen seramik lavabo dahil.",
      "isNew": true
    },
    {
      "id": 34,
      "name": "Kömürlük Kapısı - Siyah Altın Desenli",
      "category": "komurluk-kapisi",
      "image": "assets/images/products/komurluk-kapisi/komurluk-kapisi-siyah-altin.jpg",
      "description": "Ferforje işlemeli siyah gövde üzerine altın detaylı kömürlük kapısı. Dayanıklı çelik konstrüksiyon.",
      "isNew": true
    },
    {
      "id": 35,
      "name": "Yangın Kapısı - Tek Kanatlı",
      "category": "yangin-kapisi",
      "image": "assets/images/products/yangin-kapisi/yangin-kapisi-tek-kanat.jpg",
      "description": "Yangına dayanıklı çelik tek kanatlı yangın kapısı. Panik barlı, sertifikalı.",
      "isNew": true
    },
    {
      "id": 36,
      "name": "Yangın Kapısı - Çift Kanatlı",
      "category": "yangin-kapisi",
      "image": "assets/images/products/yangin-kapisi/yangin-kapisi-cift-kanat.jpg",
      "description": "Çift kanatlı sertifikalı yangın kapısı. Bina giriş ve kat arası kullanıma uygun.",
      "isNew": true
    },
    {
      "id": 37,
      "name": "Pimapen Pencere - Antrasit Çift Açılım",
      "category": "pimapen",
      "image": "assets/images/products/pimapen/pimapen-antrasit-pencere.jpg",
      "description": "Antrasit gri profilli ısı yalıtımlı çift açılımlı PVC pencere sistemi.",
      "isNew": true
    },
    {
      "id": 38,
      "name": "Pimapen Pencere - Beyaz Çeşitli",
      "category": "pimapen",
      "image": "assets/images/products/pimapen/pimapen-pencere-cesitleri.jpg",
      "description": "Farklı ebat ve modellerde beyaz PVC pencere koleksiyonu. Vasistas ve çift açılım seçenekli.",
      "isNew": true
    },
    {
      "id": 39,
      "name": "Pimapen Pencere - Thermoplast",
      "category": "pimapen",
      "image": "assets/images/products/pimapen/pimapen-pencere-thermoplast.jpg",
      "description": "Thermoplast marka ısı ve ses yalıtımlı PVC pencere. Vasistas ve çift açılımlı.",
      "isNew": true
    },
    {
      "id": 40,
      "name": "Duşakabin Kare - Siyah Buzlu Cam",
      "category": "dusakabin",
      "image": "assets/images/products/dusakabin/dusakabin-kare-siyah-buzlu.jpg",
      "description": "Siyah profilli buzlu temperli cam kare duşakabin. Endüstriyel cam bölmeli tasarım.",
      "isNew": true
    },
    {
      "id": 41,
      "name": "Duşakabin Kare - Siyah Şeffaf Cam",
      "category": "dusakabin",
      "image": "assets/images/products/dusakabin/dusakabin-kare-siyah-seffaf.jpg",
      "description": "Siyah profilli şeffaf temperli cam kare duşakabin. Sürgülü kapı sistemi.",
      "isNew": true
    },
    {
      "id": 42,
      "name": "Duşakabin Kare - Siyah Temperli",
      "category": "dusakabin",
      "image": "assets/images/products/dusakabin/dusakabin-kare-siyah-temperli.jpg",
      "description": "Siyah profilli köşe montaj kare duşakabin. 6mm temperli güvenlik camı.",
      "isNew": true
    },
    {
      "id": 43,
      "name": "Duşakabin Dikdörtgen - Buzlu Krom",
      "category": "dusakabin",
      "image": "assets/images/products/dusakabin/dusakabin-dikdortgen-buzlu-krom.jpg",
      "description": "Krom profilli buzlu cam dikdörtgen duşakabin. Çizgili desen, şık görünüm.",
      "isNew": true
    },
    {
      "id": 44,
      "name": "Duşakabin Dikdörtgen - Siyah Karo Desenli",
      "category": "dusakabin",
      "image": "assets/images/products/dusakabin/dusakabin-dikdortgen-siyah-karomezeli.jpg",
      "description": "Siyah profilli karo cam desenli dikdörtgen duşakabin. Modern banyo uyumlu.",
      "isNew": true
    },
    {
      "id": 45,
      "name": "Pimapen Kapı - Camlı Beyaz",
      "category": "pimapen",
      "image": "assets/images/products/pimapen/pimapen-kapi-camli-beyaz.jpg",
      "description": "Üst bölmesi buzlu camlı beyaz PVC kapı. Balkon ve dış mekan kullanımına uygun.",
      "isNew": true
    },
    {
      "id": 46,
      "name": "Duşakabin Boy - Siyah Kare Desenli",
      "category": "dusakabin",
      "image": "assets/images/products/dusakabin/dusakabin-boy-siyah-kare.jpg",
      "description": "Boy aynalı siyah profilli kare cam desenli duşakabin. Sürgülü kapı mekanizması.",
      "isNew": true
    },
    {
      "id": 47,
      "name": "Duşakabin Dikdörtgen - Siyah Buzlu Cam",
      "category": "dusakabin",
      "image": "assets/images/products/dusakabin/dusakabin-dikdortgen-siyah-buzlu.jpg",
      "description": "Siyah profilli buzlu temperli cam dikdörtgen duşakabin. Geniş iç mekan, sürgülü kapı.",
      "isNew": true
    },
    {
      "id": 48,
      "name": "Duşakabin Oval - Siyah Şeffaf",
      "category": "dusakabin",
      "image": "assets/images/products/dusakabin/dusakabin-oval-siyah-seffaf.jpg",
      "description": "Siyah profilli oval formlu şeffaf cam duşakabin. Kompakt banyolara uygun.",
      "isNew": true
    },
    {
      "id": 49,
      "name": "Duşakabin Dikdörtgen - Krom Çizgili",
      "category": "dusakabin",
      "image": "assets/images/products/dusakabin/dusakabin-dikdortgen-krom-cizgili.jpg",
      "description": "Krom profilli çizgi desenli dikdörtgen duşakabin. Klasik banyo dekorasyonu ile uyumlu.",
      "isNew": true
    },
    {
      "id": 50,
      "name": "Duşakabin Boy - Siyah Cam Bölmeli",
      "category": "dusakabin",
      "image": "assets/images/products/dusakabin/dusakabin-boy-siyah-cam.jpg",
      "description": "Siyah profilli boy temperli cam duşakabin. Üst sabit panel, alt sürgülü kapı.",
      "isNew": true
    },
    {
      "id": 51,
      "name": "Duşakabin Kare - Siyah Minimal",
      "category": "dusakabin",
      "image": "assets/images/products/dusakabin/dusakabin-kare-siyah-minimal.jpg",
      "description": "Minimal tasarımlı siyah profilli kare duşakabin. 6mm temperli güvenlik camı.",
      "isNew": true
    },
    {
      "id": 52,
      "name": "Duşakabin Oval - Krom Şeffaf",
      "category": "dusakabin",
      "image": "assets/images/products/dusakabin/dusakabin-oval-krom-seffaf.jpg",
      "description": "Krom profilli oval formlu şeffaf cam duşakabin. Köşe montaj, kompakt tasarım.",
      "isNew": true
    },
    {
      "id": 53,
      "name": "Duşakabin Kare - Siyah Duvara Monte",
      "category": "dusakabin",
      "image": "assets/images/products/dusakabin/dusakabin-kare-siyah-duvar.jpg",
      "description": "Duvara monte siyah profilli kare cam duşakabin. Sürgülü kapı sistemi.",
      "isNew": true
    },
    {
      "id": 54,
      "name": "Duşakabin Oval - Siyah Buzlu",
      "category": "dusakabin",
      "image": "assets/images/products/dusakabin/dusakabin-oval-siyah-buzlu.jpg",
      "description": "Siyah profilli buzlu cam oval duşakabin. Mahremiyet sağlayan buzlu cam.",
      "isNew": true
    },
    {
      "id": 55,
      "name": "Duşakabin Dikdörtgen - Siyah Geniş",
      "category": "dusakabin",
      "image": "assets/images/products/dusakabin/dusakabin-dikdortgen-siyah-genis.jpg",
      "description": "Geniş profilli siyah dikdörtgen duşakabin. Çift sürgülü kapı, geniş giriş.",
      "isNew": true
    }
  ]
}